lightningmf_pk
