Metadata-Version: 1.0
Name: lightningmf
Version: 1.0.3
Summary: Lightning MAME Frontend
Home-page: http://lightningmf.neoname.eu/
Author: Nicolas Vanhoren
Author-email: nicolas.vanhoren@unknown.com
License: GPLv3
Platform: UNKNOWN
